[
    {
        "font_family": "ff1",
        "text": "欧菲科技股份有限公司  2017  年年度报告全文",
        "bottom": 790.32,
        "data_offset_end": 30,
        "font_size": 36.0,
        "left": 363.16,
        "line_height": 0,
        "data_offset_start": 6,
        "text_shadow": "-0.015em 0 transparent,0 0.015em transparent,0.015em 0 transparent,0 -0.015em transparent",
        "height": 33.66,
        "level": "BTitle_9999"
    },
    {
        "font_family": "ff2",
        "text": "102姓名职务报告期内可行权股数报告期内已行权股数报告期内已行权股数行权价格 （元 /股）报告期末市价（元 /股）期初持有限制性股票数量本期已解锁股份数量报告期新授予限制性股票数量限制性股票的授予价格（元 /股）期末持有限制性股票数量黄丽辉董事0000500,000375,00000875,000关赛新董事0000637,200477,900001,1 15,100宣利监事0000100,00075,00000175,000海江监事0000637,200477,900001,1 15,100谭振林总经理0000600,000450,000001,050,000郭剑副总经理0000400,000300,00000700,000唐根初副总经理0000300,000225,00000525,000孟锴副总经理0000937,200702,900001,640,100李素雯财务总监0000600,000450,000001,050,000肖燕松董事会秘书、 副总经理0000600,000450,000001,050,000合计--00----5,31 1,6003,983,7000--9,295,300备注（如有）2017  年 6月 12 日，公司实施 2016  年度权益分派，以公积金转增股本，每 10  股转增 15  股。公司高级管理人员获授的限制性股票数目相应转增。  2017 年9月11 日，公司限制性股票激励计划第一个解锁期解锁条件达成，解锁比例为  30% 。",
        "bottom": 51.72,
        "data_offset_end": 951,
        "font_size": 36.0,
        "left": 525.18,
        "line_height": 0,
        "data_offset_start": 31,
        "text_shadow": "-0.015em 0 transparent,0 0.015em transparent,0.015em 0 transparent,0 -0.015em transparent",
        "height": 33.66,
        "level": "BTitle_9999"
    },
    {
        "font_family": "ff1",
        "text": "五、公司员工情况",
        "bottom": 371.72,
        "data_offset_end": 961,
        "font_size": 48.0,
        "left": 56.94,
        "line_height": 0,
        "data_offset_start": 952,
        "text_shadow": "-0.015em 0 rgb(0,0,0),0 0.015em rgb(0,0,0),0.015em 0 rgb(0,0,0),0 -0.015em rgb(0,0,0)",
        "height": 44.88,
        "level": "ATitle_9999"
    },
    {
        "font_family": "ff3",
        "text": "1 、员工数量、专业构成及教育程度",
        "bottom": 341.66,
        "data_offset_end": 979,
        "font_size": 42.0,
        "left": 56.94,
        "line_height": 0,
        "data_offset_start": 962,
        "text_shadow": "-0.015em 0 transparent,0 0.015em transparent,0.015em 0 transparent,0 -0.015em transparent",
        "height": 39.27,
        "level": "BTitle_9999"
    },
    {
        "font_family": "ff1",
        "text": "母公司在职员工的数量（人）3,546主要子公司在职员工的数量（人）38,280在职员工的数量合计（人）41,826当期领取薪酬员工总人数（人）41,826母公司及主要子公司需承担费用的离退休职工人数（人）0专业构成专业构成类别专业构成人数（人）生产人员35,949销售人员1 18技术人员3,905财务人员123行政人员1,731",
        "bottom": 6.48,
        "data_offset_end": 1189,
        "font_size": 36.0,
        "left": 1.14,
        "line_height": 0,
        "data_offset_start": 980,
        "text_shadow": "-0.015em 0 transparent,0 0.015em transparent,0.015em 0 transparent,0 -0.015em transparent",
        "height": 33.66,
        "level": "BTitle_9999"
    }
]