[
    {
        "font_family": "ff1",
        "text": "欧菲科技股份有限公司  2017  年年度报告全文",
        "bottom": 790.32,
        "data_offset_end": 30,
        "font_size": 36.0,
        "left": 363.16,
        "line_height": 0,
        "data_offset_start": 6,
        "text_shadow": "-0.015em 0 transparent,0 0.015em transparent,0.015em 0 transparent,0 -0.015em transparent",
        "height": 33.66,
        "level": "Text_9999"
    },
    {
        "font_family": "ff2",
        "text": "3",
        "bottom": 51.72,
        "data_offset_end": 33,
        "font_size": 36.0,
        "left": 534.18,
        "line_height": 0,
        "data_offset_start": 31,
        "text_shadow": "-0.015em 0 transparent,0 0.015em transparent,0.015em 0 transparent,0 -0.015em transparent",
        "height": 33.66,
        "level": "Text_9999"
    },
    {
        "font_family": "ff1",
        "text": "目录",
        "bottom": 682.84,
        "data_offset_end": 37,
        "font_size": 72.0,
        "left": 279.64,
        "line_height": 0,
        "data_offset_start": 34,
        "text_shadow": "-0.015em 0 rgb(0,0,0),0 0.015em rgb(0,0,0),0.015em 0 rgb(0,0,0),0 -0.015em rgb(0,0,0)",
        "height": 67.32,
        "level": "ATitle_9999"
    },
    {
        "font_family": "ff1",
        "text": "第一节   重要提示、目录和释义 ........................................................................................................ 7",
        "bottom": 591.64,
        "data_offset_end": 160,
        "font_size": 48.0,
        "left": 56.7,
        "line_height": 0,
        "data_offset_start": 38,
        "text_shadow": "-0.015em 0 rgb(0,0,0),0 0.015em rgb(0,0,0),0.015em 0 rgb(0,0,0),0 -0.015em rgb(0,0,0)",
        "height": 44.88,
        "level": "BTitle_9999"
    },
    {
        "font_family": "ff1",
        "text": "第二节   公司简介和主要财务指标 .................................................................................................. 11",
        "bottom": 567.04,
        "data_offset_end": 279,
        "font_size": 48.0,
        "left": 56.7,
        "line_height": 0,
        "data_offset_start": 161,
        "text_shadow": "-0.015em 0 rgb(0,0,0),0 0.015em rgb(0,0,0),0.015em 0 rgb(0,0,0),0 -0.015em rgb(0,0,0)",
        "height": 44.88,
        "level": "BTitle_9999"
    },
    {
        "font_family": "ff1",
        "text": "第三节   公司业务概要 ...................................................................................................................... 21",
        "bottom": 542.44,
        "data_offset_end": 413,
        "font_size": 48.0,
        "left": 56.7,
        "line_height": 0,
        "data_offset_start": 280,
        "text_shadow": "-0.015em 0 rgb(0,0,0),0 0.015em rgb(0,0,0),0.015em 0 rgb(0,0,0),0 -0.015em rgb(0,0,0)",
        "height": 44.88,
        "level": "BTitle_9999"
    },
    {
        "font_family": "ff1",
        "text": "第四节   经营情况讨论与分析 .......................................................................................................... 62",
        "bottom": 517.84,
        "data_offset_end": 538,
        "font_size": 48.0,
        "left": 56.7,
        "line_height": 0,
        "data_offset_start": 414,
        "text_shadow": "-0.015em 0 rgb(0,0,0),0 0.015em rgb(0,0,0),0.015em 0 rgb(0,0,0),0 -0.015em rgb(0,0,0)",
        "height": 44.88,
        "level": "BTitle_9999"
    },
    {
        "font_family": "ff1",
        "text": "第五节   重要事项 .............................................................................................................................. 85",
        "bottom": 493.24,
        "data_offset_end": 678,
        "font_size": 48.0,
        "left": 56.7,
        "line_height": 0,
        "data_offset_start": 539,
        "text_shadow": "-0.015em 0 rgb(0,0,0),0 0.015em rgb(0,0,0),0.015em 0 rgb(0,0,0),0 -0.015em rgb(0,0,0)",
        "height": 44.88,
        "level": "BTitle_9999"
    },
    {
        "font_family": "ff1",
        "text": "第六节   股份变动及股东情况 .......................................................................................................... 94",
        "bottom": 468.64,
        "data_offset_end": 803,
        "font_size": 48.0,
        "left": 56.7,
        "line_height": 0,
        "data_offset_start": 679,
        "text_shadow": "-0.015em 0 rgb(0,0,0),0 0.015em rgb(0,0,0),0.015em 0 rgb(0,0,0),0 -0.015em rgb(0,0,0)",
        "height": 44.88,
        "level": "BTitle_9999"
    },
    {
        "font_family": "ff1",
        "text": "第七节   优先股相关情况 .................................................................................................................. 94",
        "bottom": 444.04,
        "data_offset_end": 934,
        "font_size": 48.0,
        "left": 56.7,
        "line_height": 0,
        "data_offset_start": 804,
        "text_shadow": "-0.015em 0 rgb(0,0,0),0 0.015em rgb(0,0,0),0.015em 0 rgb(0,0,0),0 -0.015em rgb(0,0,0)",
        "height": 44.88,
        "level": "BTitle_9999"
    },
    {
        "font_family": "ff1",
        "text": "第八节   董事、监事、高级管理人员和员工情况 .......................................................................... 95",
        "bottom": 419.42,
        "data_offset_end": 1035,
        "font_size": 48.0,
        "left": 56.7,
        "line_height": 0,
        "data_offset_start": 935,
        "text_shadow": "-0.015em 0 rgb(0,0,0),0 0.015em rgb(0,0,0),0.015em 0 rgb(0,0,0),0 -0.015em rgb(0,0,0)",
        "height": 44.88,
        "level": "BTitle_9999"
    },
    {
        "font_family": "ff1",
        "text": "第九节   公司治理 ............................................................................................................................ 104",
        "bottom": 394.82,
        "data_offset_end": 1174,
        "font_size": 48.0,
        "left": 56.7,
        "line_height": 0,
        "data_offset_start": 1036,
        "text_shadow": "-0.015em 0 rgb(0,0,0),0 0.015em rgb(0,0,0),0.015em 0 rgb(0,0,0),0 -0.015em rgb(0,0,0)",
        "height": 44.88,
        "level": "BTitle_9999"
    },
    {
        "font_family": "ff1",
        "text": "第十节   公司债券相关情况 ............................................................................................................ 112",
        "bottom": 370.22,
        "data_offset_end": 1301,
        "font_size": 48.0,
        "left": 56.7,
        "line_height": 0,
        "data_offset_start": 1175,
        "text_shadow": "-0.015em 0 rgb(0,0,0),0 0.015em rgb(0,0,0),0.015em 0 rgb(0,0,0),0 -0.015em rgb(0,0,0)",
        "height": 44.88,
        "level": "BTitle_9999"
    },
    {
        "font_family": "ff1",
        "text": "第十一节  财务报告  ........................................................................................................................ 117",
        "bottom": 345.62,
        "data_offset_end": 1437,
        "font_size": 48.0,
        "left": 56.7,
        "line_height": 0,
        "data_offset_start": 1302,
        "text_shadow": "-0.015em 0 rgb(0,0,0),0 0.015em rgb(0,0,0),0.015em 0 rgb(0,0,0),0 -0.015em rgb(0,0,0)",
        "height": 44.88,
        "level": "BTitle_9999"
    },
    {
        "font_family": "ff1",
        "text": "第十二节   备查文件目录 ................................................................................................................ 250",
        "bottom": 321.02,
        "data_offset_end": 1567,
        "font_size": 48.0,
        "left": 56.7,
        "line_height": 0,
        "data_offset_start": 1438,
        "text_shadow": "-0.015em 0 rgb(0,0,0),0 0.015em rgb(0,0,0),0.015em 0 rgb(0,0,0),0 -0.015em rgb(0,0,0)",
        "height": 44.88,
        "level": "BTitle_9999"
    }
]