[
    {
        "font_family": "ff1",
        "text": "欧菲科技股份有限公司  2017  年年度报告全文",
        "bottom": 790.32,
        "data_offset_end": 30,
        "font_size": 36.0,
        "left": 363.16,
        "line_height": 0,
        "data_offset_start": 6,
        "text_shadow": "-0.015em 0 transparent,0 0.015em transparent,0.015em 0 transparent,0 -0.015em transparent",
        "height": 33.66,
        "level": "BTitle_9999"
    },
    {
        "font_family": "ff2",
        "text": "207补贴资金疲劳驾驶预警控制器关键技术研发与产业化项目4,500,000.004,500,000.00与收益相关合计21,781,032.889,200,000.007,949,532.290.000.0023,031,500.59--其他说明：",
        "bottom": 51.72,
        "data_offset_end": 196,
        "font_size": 36.0,
        "left": 525.18,
        "line_height": 0,
        "data_offset_start": 31,
        "text_shadow": "-0.015em 0 transparent,0 0.015em transparent,0.015em 0 transparent,0 -0.015em transparent",
        "height": 33.66,
        "level": "BTitle_9999"
    },
    {
        "font_family": "ff3",
        "text": "43 、其他非流动负债",
        "bottom": 588.94,
        "data_offset_end": 208,
        "font_size": 42.0,
        "left": 56.94,
        "line_height": 0,
        "data_offset_start": 197,
        "text_shadow": "-0.015em 0 transparent,0 0.015em transparent,0.015em 0 transparent,0 -0.015em transparent",
        "height": 39.27,
        "level": "ATitle_9999"
    },
    {
        "font_family": "ff1",
        "text": "单位：  元项目期末余额期初余额退职年金负债2,236,673.08737,266.76销售产品分期预收账款1,989,485.281,989,485.28合计4,226,158.362,726,752.04其他说明：",
        "bottom": 558.76,
        "data_offset_end": 344,
        "font_size": 36.0,
        "left": 498.18,
        "line_height": 0,
        "data_offset_start": 209,
        "text_shadow": "-0.015em 0 transparent,0 0.015em transparent,0.015em 0 transparent,0 -0.015em transparent",
        "height": 33.66,
        "level": "BTitle_9999"
    },
    {
        "font_family": "ff3",
        "text": "44 、股本",
        "bottom": 427.18,
        "data_offset_end": 351,
        "font_size": 42.0,
        "left": 56.94,
        "line_height": 0,
        "data_offset_start": 345,
        "text_shadow": "-0.015em 0 transparent,0 0.015em transparent,0.015em 0 transparent,0 -0.015em transparent",
        "height": 39.27,
        "level": "ATitle_9999"
    },
    {
        "font_family": "ff1",
        "text": "单位：元期初余额本次变动增减（ +、 —）期末余额发行新股送股公积金转股其他小计股份总数1,086,266,390.001,629,399,585.00-1,220,000.001,628,179,585.002,714,445,975.00其他说明：",
        "bottom": 396.98,
        "data_offset_end": 514,
        "font_size": 36.0,
        "left": 502.68,
        "line_height": 0,
        "data_offset_start": 352,
        "text_shadow": "-0.015em 0 transparent,0 0.015em transparent,0.015em 0 transparent,0 -0.015em transparent",
        "height": 33.66,
        "level": "BTitle_9999"
    },
    {
        "font_family": "ff1",
        "text": "根据欧菲光公司 2017年 5月 16日 2016年年度股东大会决议和 2017年 4月第三届董事会第三十八次会议决议，欧菲光公司以总股本 1,086,266,390股为基数，以资本公积转增股本，每 10股转增 15股，申请增加股本 1,629,399,585股，本期限制性股票回购注销 1,220,000.00股。",
        "bottom": 282.92,
        "data_offset_end": 665,
        "font_size": 42.0,
        "left": 77.7,
        "line_height": 0,
        "data_offset_start": 515,
        "text_shadow": "-0.015em 0 transparent,0 0.015em transparent,0.015em 0 transparent,0 -0.015em transparent",
        "height": 39.27,
        "level": "ATitle_9999"
    },
    {
        "font_family": "ff2",
        "text": "",
        "bottom": 236.72,
        "data_offset_end": 666,
        "font_size": 36.0,
        "left": 56.94,
        "line_height": 0,
        "data_offset_start": 666,
        "text_shadow": "-0.015em 0 transparent,0 0.015em transparent,0.015em 0 transparent,0 -0.015em transparent",
        "height": 33.66,
        "level": "BTitle_9999"
    },
    {
        "font_family": "ff3",
        "text": "45 、资本公积",
        "bottom": 205.46,
        "data_offset_end": 675,
        "font_size": 42.0,
        "left": 56.94,
        "line_height": 0,
        "data_offset_start": 667,
        "text_shadow": "-0.015em 0 transparent,0 0.015em transparent,0.015em 0 transparent,0 -0.015em transparent",
        "height": 39.27,
        "level": "ATitle_9999"
    },
    {
        "font_family": "ff1",
        "text": "单位：  元项目期初余额本期增加本期减少期末余额资本溢价（股本溢价）4,469,412,321.0460,823,000.661,629,399,585.002,900,835,736.70其他资本公积53,406,509.61292,964,857.1 166,557,000.66279,814,366.06合计4,522,818,830.65353,787,857.771,695,956,585.663,180,650,102.76其他说明，包括本期增减变动情况、变动原因说明：",
        "bottom": 175.28,
        "data_offset_end": 960,
        "font_size": 36.0,
        "left": 498.18,
        "line_height": 0,
        "data_offset_start": 676,
        "text_shadow": "-0.015em 0 transparent,0 0.015em transparent,0.015em 0 transparent,0 -0.015em transparent",
        "height": 33.66,
        "level": "BTitle_9999"
    }
]