[
    {
        "data-offset-end": 9,
        "pageid": 161,
        "top": 153,
        "font-id": "f8",
        "level": "Level",
        "left": 1240,
        "text": "綜合財務報表附註",
        "font-size": 51,
        "color": "rgba(222,129,14,1)",
        "data-offset-start": 2
    },
    {
        "data-offset-end": 27,
        "pageid": 161,
        "top": 215,
        "font-id": "f10",
        "level": "Level",
        "left": 1187,
        "text": "截至二零一七年十二月三十一日止年度",
        "font-size": 27,
        "color": "rgba(35,31,31,1)",
        "data-offset-start": 11
    },
    {
        "data-offset-end": 75,
        "pageid": 161,
        "top": 535,
        "font-id": "f13",
        "level": "Level",
        "left": 263,
        "text": "於聯營公司的權益投資變動分析如下：",
        "font-size": 27,
        "color": "rgba(35,31,31,1)",
        "data-offset-start": 59
    },
    {
        "data-offset-end": 131,
        "pageid": 161,
        "top": 906,
        "font-id": "f13",
        "level": "Level",
        "left": 280,
        "text": "添置：",
        "font-size": 27,
        "color": "rgba(35,31,31,1)",
        "data-offset-start": 129
    },
    {
        "data-offset-end": 242,
        "pageid": 161,
        "top": 1221,
        "font-id": "f13",
        "level": "Level",
        "left": 280,
        "text": "出售：",
        "font-size": 27,
        "color": "rgba(35,31,31,1)",
        "data-offset-start": 240
    },
    {
        "data-offset-end": 556,
        "pageid": 161,
        "top": 1585,
        "font-id": "f13",
        "level": "Level",
        "left": 263,
        "text": "附註：",
        "font-size": 22,
        "color": "rgba(35,31,31,1)",
        "data-offset-start": 554
    },
    {
        "data-offset-end": 576,
        "pageid": 161,
        "top": 1663,
        "font-id": "f14",
        "level": "Level",
        "left": 263,
        "text": "(a)收購聯營公司主要包括下列投資：",
        "font-size": 22,
        "color": "rgba(35,31,31,1)",
        "data-offset-start": 558
    },
    {
        "data-offset-end": 730,
        "pageid": 161,
        "top": 1741,
        "font-id": "f13",
        "level": "Level",
        "left": 331,
        "text": "於二零一七年，本集團以總代價人民幣15,461百萬元分別收購樂視網信息技術（北京）股份有限公司（「樂視網」）、新樂視智家電子科技（天津）有限公司（「樂視智家」，前稱樂視致新電子科技（天津）有限公司）及樂視影業（北京）有限公司（「樂視影業」）（統稱「樂視相關公司」）8.56%、33.5%及21%的權益。",
        "font-size": 22,
        "color": "rgba(35,31,31,1)",
        "data-offset-start": 578
    },
    {
        "data-offset-end": 890,
        "pageid": 161,
        "top": 1897,
        "font-id": "f13",
        "level": "Level",
        "left": 331,
        "text": "樂視網為一家於中國成立的有限公司，其股份於深圳證券交易所上市。樂視網主要從事視頻平台廣告服務，按需求提供視頻會員服務。樂視智家為樂視網的一家附屬公司，主要從事網絡及智能電視的研發、製作及銷售業務。樂視影業為一家於中國成立的有限公司，其主要業務活動為投資及電影製作及發行、電影授權及分授權以及電視版權經營及業務發展。",
        "font-size": 22,
        "color": "rgba(35,31,31,1)",
        "data-offset-start": 732
    },
    {
        "data-offset-end": 970,
        "pageid": 161,
        "top": 2053,
        "font-id": "f13",
        "level": "Level",
        "left": 331,
        "text": "本集團估計其於收購日期應佔樂視公司可識別資產及負債的公允價值淨值。代價超出本集團應佔樂視公司資產淨值的公允價值的差額，入賬為商譽，並計入該等投資的賬面值內。",
        "font-size": 22,
        "color": "rgba(35,31,31,1)",
        "data-offset-start": 892
    },
    {
        "data-offset-end": 1076,
        "pageid": 161,
        "top": 2170,
        "font-id": "f13",
        "level": "Level",
        "left": 331,
        "text": "於二零一七年十二月三十一日，除上述樂視相關公司投資外，本集團亦以代價人民幣1,300百萬元收購樂視智家及樂視影業的額外股權（定義見附註17「樂視預付投資」）。樂視相關公司投資及樂視預付投資統稱為「樂視投資」。",
        "font-size": 22,
        "color": "rgba(35,31,31,1)",
        "data-offset-start": 972
    },
    {
        "data-offset-end": 1091,
        "pageid": 161,
        "top": 2303,
        "font-id": "f8",
        "level": "Level",
        "left": 1412,
        "text": "融創中國控股有限公司159",
        "font-size": 24,
        "color": "rgba(222,129,14,1)",
        "data-offset-start": 1078
    },
    {
        "data-offset-end": 1100,
        "pageid": 161,
        "top": 2330,
        "font-id": "f9",
        "level": "Level",
        "left": 1504,
        "text": "2017年度報告",
        "font-size": 24,
        "color": "rgba(101,98,98,1)",
        "data-offset-start": 1093
    }
]