[
    {
        "line_height": 0,
        "font_family": "ff1",
        "bottom": 790.32,
        "text": "美的集团股份有限公司  2017  年年度报告8",
        "font_size": 36.0,
        "text_shadow": "-0.015em 0 transparent,0 0.015em transparent,0.015em 0 transparent,0 -0.015em transparent",
        "left": 381.07,
        "data_offset_end": 31,
        "data_offset_start": 6,
        "level": "BTitle_9999",
        "height": 33.66
    },
    {
        "line_height": 0,
        "font_family": "ff1",
        "bottom": 730.54,
        "text": "第二节   公司简介和主要财务指标",
        "font_size": 63.84,
        "text_shadow": "-0.015em 0 rgb(0,0,0),0 0.015em rgb(0,0,0),0.015em 0 rgb(0,0,0),0 -0.015em rgb(0,0,0)",
        "left": 181.13,
        "data_offset_end": 48,
        "data_offset_start": 32,
        "level": "ATitle_9999",
        "height": 59.6904
    },
    {
        "line_height": 0,
        "font_family": "ff1",
        "bottom": 688.66,
        "text": "一、公司信息",
        "font_size": 48.0,
        "text_shadow": "-0.015em 0 rgb(0,0,0),0 0.015em rgb(0,0,0),0.015em 0 rgb(0,0,0),0 -0.015em rgb(0,0,0)",
        "left": 56.664,
        "data_offset_end": 56,
        "data_offset_start": 49,
        "level": "BTitle_9999",
        "height": 44.88
    },
    {
        "line_height": 0,
        "font_family": "ff1",
        "bottom": 6.72,
        "text": "股票简称美的集团股票代码000333股票上市证券交易所深圳证券交易所公司的中文名称美的集团股份有限公司公司的中文简称美的集团公司的外文名称（如有）Midea Group Co., Ltd.公司的外文名称缩写 （如有）Midea Group公司的法定代表人方洪波注册地址广东省佛山市顺德区北滘镇美的大道  6 号美的总部大楼注册地址的邮政编码52831 1办公地址广东省佛山市顺德区北滘镇美的大道  6 号美的总部大楼办公地址的邮政编码52831 1公司网址http://www .midea.com电子信箱IR@midea.com",
        "font_size": 36.0,
        "text_shadow": "-0.015em 0 transparent,0 0.015em transparent,0.015em 0 transparent,0 -0.015em transparent",
        "left": 1.073,
        "data_offset_end": 369,
        "data_offset_start": 57,
        "level": "BTitle_9999",
        "height": 33.66
    },
    {
        "line_height": 0,
        "font_family": "ff1",
        "bottom": 381.17,
        "text": "二、联系人和 联系方式",
        "font_size": 48.0,
        "text_shadow": "-0.015em 0 rgb(0,0,0),0 0.015em rgb(0,0,0),0.015em 0 rgb(0,0,0),0 -0.015em rgb(0,0,0)",
        "left": 56.664,
        "data_offset_end": 381,
        "data_offset_start": 370,
        "level": "BTitle_9999",
        "height": 44.88
    },
    {
        "line_height": 0,
        "font_family": "ff2",
        "bottom": 6.72,
        "text": "董事会秘书证券事务代表姓名江鹏欧云彬联系地址广东省佛山市顺德区北滘镇美的大道  6 号美的总部大楼电话0757-226077080757-23274957传真0757-26605456电子信箱IR@midea.com",
        "font_size": 36.0,
        "text_shadow": "-0.015em 0 transparent,0 0.015em transparent,0.015em 0 transparent,0 -0.015em transparent",
        "left": 79.429,
        "data_offset_end": 516,
        "data_offset_start": 382,
        "level": "BTitle_9999",
        "height": 33.66
    },
    {
        "line_height": 0,
        "font_family": "ff1",
        "bottom": 214.46,
        "text": "三、信息披露 及备置地点",
        "font_size": 48.0,
        "text_shadow": "-0.015em 0 rgb(0,0,0),0 0.015em rgb(0,0,0),0.015em 0 rgb(0,0,0),0 -0.015em rgb(0,0,0)",
        "left": 56.664,
        "data_offset_end": 529,
        "data_offset_start": 517,
        "level": "BTitle_9999",
        "height": 44.88
    },
    {
        "line_height": 0,
        "font_family": "ff1",
        "bottom": 6.71,
        "text": "公司选定的信息披露媒体的名称《中国证券报》 、 《证券时报》 、 《上海证券报》登载年度报告的中国证监会指定网站的网址http://www .cninfo.com.cn公司年度报告备置地点公司董事会办公室",
        "font_size": 36.0,
        "text_shadow": "-0.015em 0 transparent,0 0.015em transparent,0.015em 0 transparent,0 -0.015em transparent",
        "left": 1.073,
        "data_offset_end": 638,
        "data_offset_start": 530,
        "level": "BTitle_9999",
        "height": 33.66
    }
]