[
    {
        "line_height": 0,
        "font_family": "ff1",
        "bottom": 790.32,
        "text": "美的集团股份有限公司  2017  年年度报告",
        "font_size": 36.0,
        "text_shadow": "-0.015em 0 transparent,0 0.015em transparent,0.015em 0 transparent,0 -0.015em transparent",
        "left": 381.07,
        "data_offset_end": 28,
        "data_offset_start": 6,
        "level": "Text_9999",
        "height": 33.66
    },
    {
        "line_height": 0,
        "font_family": "ff2",
        "bottom": 51.744,
        "text": "39",
        "font_size": 36.0,
        "text_shadow": "-0.015em 0 transparent,0 0.015em transparent,0.015em 0 transparent,0 -0.015em transparent",
        "left": 293.11,
        "data_offset_end": 32,
        "data_offset_start": 29,
        "level": "CTitle_9999",
        "height": 33.66
    },
    {
        "line_height": 0,
        "font_family": "ff1",
        "bottom": 730.54,
        "text": "第五节  重要事项",
        "font_size": 63.84,
        "text_shadow": "-0.015em 0 rgb(0,0,0),0 0.015em rgb(0,0,0),0.015em 0 rgb(0,0,0),0 -0.015em rgb(0,0,0)",
        "left": 237.41,
        "data_offset_end": 42,
        "data_offset_start": 33,
        "level": "ATitle_9999",
        "height": 59.6904
    },
    {
        "line_height": 0,
        "font_family": "ff1",
        "bottom": 688.66,
        "text": "一、公司普通 股利润分配及资 本公积金转增股本 情况",
        "font_size": 48.0,
        "text_shadow": "-0.015em 0 rgb(0,0,0),0 0.015em rgb(0,0,0),0.015em 0 rgb(0,0,0),0 -0.015em rgb(0,0,0)",
        "left": 56.664,
        "data_offset_end": 67,
        "data_offset_start": 43,
        "level": "BTitle_9999",
        "height": 44.88
    },
    {
        "line_height": 0,
        "font_family": "ff1",
        "bottom": 658.54,
        "text": "报告期内普通股 利润分配政策， 特别是现金分 红政策的制定、 执行或调整情 况",
        "font_size": 42.24,
        "text_shadow": "-0.015em 0 transparent,0 0.015em transparent,0.015em 0 transparent,0 -0.015em transparent",
        "left": 56.664,
        "data_offset_end": 103,
        "data_offset_start": 68,
        "level": "Text_9999",
        "height": 35.145
    },
    {
        "line_height": 0,
        "font_family": "ff1",
        "bottom": 636.94,
        "text": "□   适用  √  不适用",
        "font_size": 42.24,
        "text_shadow": "-0.015em 0 transparent,0 0.015em transparent,0.015em 0 transparent,0 -0.015em transparent",
        "left": 56.664,
        "data_offset_end": 115,
        "data_offset_start": 104,
        "level": "Text_9999",
        "height": 35.145
    },
    {
        "line_height": 0,
        "font_family": "ff1",
        "bottom": 615.34,
        "text": "公司近  3 年（包括本报告期）的普通股股利分配方案（预案）、资本公积金转增股本方案（预案）情况",
        "font_size": 42.24,
        "text_shadow": "-0.015em 0 transparent,0 0.015em transparent,0.015em 0 transparent,0 -0.015em transparent",
        "left": 56.664,
        "data_offset_end": 163,
        "data_offset_start": 116,
        "level": "Text_9999",
        "height": 35.145
    },
    {
        "line_height": 0,
        "font_family": "ff4",
        "bottom": 589.9,
        "text": "2015  年度利润分配及资本公积金转增股本方案为：以公司总股本 4,267,391,228 股为基数，向全体股东每  10  股派发现金 12 元（含税），同时以资本公积金向全体股东每 10 股转增 5股。股权登记日为 2016年 5月 5 日，除权除息日为 2016 年5月6日。",
        "font_size": 42.24,
        "text_shadow": "-0.015em 0 transparent,0 0.015em transparent,0.015em 0 transparent,0 -0.015em transparent",
        "left": 77.664,
        "data_offset_end": 303,
        "data_offset_start": 164,
        "level": "Text_9999",
        "height": 35.145
    },
    {
        "line_height": 0,
        "font_family": "ff4",
        "bottom": 517.63,
        "text": "2016  年度利润分配方案为：以公司现有总股本 6,465,677,368 股为基数，向全体股东每 10 股派发现金 10  元（含税）。股权登记日为 2017 年5月9日，除权除息日为 2017 年5月10 日。",
        "font_size": 42.24,
        "text_shadow": "-0.015em 0 transparent,0 0.015em transparent,0.015em 0 transparent,0 -0.015em transparent",
        "left": 77.664,
        "data_offset_end": 411,
        "data_offset_start": 304,
        "level": "Text_9999",
        "height": 35.145
    },
    {
        "line_height": 0,
        "font_family": "ff4",
        "bottom": 468.91,
        "text": "2017  年度利润分配预案为：以公司现有总股本 6,584,022,574 股为基数，向全体股东每 10 股派发现金 12  元（含税）。该预案已经公司第二届董事会第三十次会议审议通过，拟提交公司股东大会审议。",
        "font_size": 42.24,
        "text_shadow": "-0.015em 0 transparent,0 0.015em transparent,0.015em 0 transparent,0 -0.015em transparent",
        "left": 77.664,
        "data_offset_end": 517,
        "data_offset_start": 412,
        "level": "Text_9999",
        "height": 35.145
    },
    {
        "line_height": 0,
        "font_family": "ff1",
        "bottom": 420.07,
        "text": "美的集团从  2013 年整体上市至今，高度重视投资者回报，已累计现金分红达 270 亿元，每年的现金分红金额占当年 度的归母净利润 的比例 超过  40%， 公司至少每三年 重新审定一次未 来股东回报规 划，保障利润分配政策的 持续性与稳定性 。公司近三年（包 括本报告期）普 通股现金分红 情况表",
        "font_size": 42.24,
        "text_shadow": "-0.015em 0 transparent,0 0.015em transparent,0.015em 0 transparent,0 -0.015em transparent",
        "left": 77.664,
        "data_offset_end": 659,
        "data_offset_start": 518,
        "level": "Text_9999",
        "height": 35.145
    },
    {
        "line_height": 0,
        "font_family": "ff1",
        "bottom": 326.81,
        "text": "单位：元分红年度现金分红金额（含税）分红年度合并报表中归属于上市公司普通股股东的净利润占合并报表中归属于上市公司普通股股东的净利润的比率以其他方式现金分红的金额以其他方式现金分红的比例2017  年7,900,827,088.8017,2 83,68 9,000.0045.71%0.000.002016  年6,465,677,368.0014,684,357,000.0044.03%0.000.002015  年5,120,869,473.6012,706,725,000.0040.30%0.000.00",
        "font_size": 36.0,
        "text_shadow": "-0.015em 0 transparent,0 0.015em transparent,0.015em 0 transparent,0 -0.015em transparent",
        "left": 502.68,
        "data_offset_end": 967,
        "data_offset_start": 660,
        "level": "Text_9999",
        "height": 33.66
    },
    {
        "line_height": 0,
        "font_family": "ff1",
        "bottom": 192.5,
        "text": "公司报告期内盈 利且母公司可供 普通股股东分 配利润为正但未 提出普通股现 金红利分配预案",
        "font_size": 42.24,
        "text_shadow": "-0.015em 0 transparent,0 0.015em transparent,0.015em 0 transparent,0 -0.015em transparent",
        "left": 56.664,
        "data_offset_end": 1009,
        "data_offset_start": 968,
        "level": "Text_9999",
        "height": 39.4944
    },
    {
        "line_height": 0,
        "font_family": "ff1",
        "bottom": 166.94,
        "text": "□   适用  √  不适用",
        "font_size": 42.24,
        "text_shadow": "-0.015em 0 transparent,0 0.015em transparent,0.015em 0 transparent,0 -0.015em transparent",
        "left": 56.664,
        "data_offset_end": 1021,
        "data_offset_start": 1010,
        "level": "Text_9999",
        "height": 35.145
    },
    {
        "line_height": 0,
        "font_family": "ff1",
        "bottom": 135.86,
        "text": "二、本报告期 利润分配及资本 公积金转增股本预 案",
        "font_size": 48.0,
        "text_shadow": "-0.015em 0 rgb(0,0,0),0 0.015em rgb(0,0,0),0.015em 0 rgb(0,0,0),0 -0.015em rgb(0,0,0)",
        "left": 56.664,
        "data_offset_end": 1045,
        "data_offset_start": 1022,
        "level": "Text_9999",
        "height": 44.88
    },
    {
        "line_height": 0,
        "font_family": "ff1",
        "bottom": 105.74,
        "text": "√   适用  □  不适用",
        "font_size": 42.24,
        "text_shadow": "-0.015em 0 transparent,0 0.015em transparent,0.015em 0 transparent,0 -0.015em transparent",
        "left": 56.664,
        "data_offset_end": 1057,
        "data_offset_start": 1046,
        "level": "Text_9999",
        "height": 35.145
    },
    {
        "line_height": 0,
        "font_family": "ff1",
        "bottom": 6.595,
        "text": "每 10  股送红股数（股）0",
        "font_size": 36.0,
        "text_shadow": "-0.015em 0 transparent,0 0.015em transparent,0.015em 0 transparent,0 -0.015em transparent",
        "left": 1.073,
        "data_offset_end": 1074,
        "data_offset_start": 1058,
        "level": "Text_9999",
        "height": 33.66
    }
]