[
    {
        "line_height": 0,
        "font_family": "ff1",
        "bottom": 785.4,
        "text": "美的集团股份有限公司",
        "font_size": 48.0,
        "text_shadow": "-0.015em 0 transparent,0 0.015em transparent,0.015em 0 transparent,0 -0.015em transparent",
        "left": 121.82,
        "data_offset_end": 17,
        "data_offset_start": 6,
        "level": "ATitle_9999",
        "height": 46.176
    },
    {
        "line_height": 0,
        "font_family": "ff2",
        "bottom": 768.84,
        "text": "",
        "font_size": 48.0,
        "text_shadow": "-0.015em 0 transparent,0 0.015em transparent,0.015em 0 transparent,0 -0.015em transparent",
        "left": 121.82,
        "data_offset_end": 18,
        "data_offset_start": 18,
        "level": "ATitle_9999",
        "height": 46.176
    },
    {
        "line_height": 0,
        "font_family": "ff2",
        "bottom": 752.14,
        "text": "2017  年度财务报表附注",
        "font_size": 48.0,
        "text_shadow": "-0.015em 0 transparent,0 0.015em transparent,0.015em 0 transparent,0 -0.015em transparent",
        "left": 121.82,
        "data_offset_end": 33,
        "data_offset_start": 19,
        "level": "ATitle_9999",
        "height": 46.176
    },
    {
        "line_height": 0,
        "font_family": "ff3",
        "bottom": 734.5,
        "text": "( 除特别注明外，金额单位为人民币千元 )",
        "font_size": 48.0,
        "text_shadow": "-0.015em 0 transparent,0 0.015em transparent,0.015em 0 transparent,0 -0.015em transparent",
        "left": 121.82,
        "data_offset_end": 55,
        "data_offset_start": 34,
        "level": "ATitle_9999",
        "height": 44.88
    },
    {
        "line_height": 0,
        "font_family": "ff2",
        "bottom": 38.4,
        "text": "183",
        "font_size": 36.0,
        "text_shadow": "-0.015em 0 transparent,0 0.015em transparent,0.015em 0 transparent,0 -0.015em transparent",
        "left": 297.43,
        "data_offset_end": 60,
        "data_offset_start": 56,
        "level": "Text_9999",
        "height": 34.632
    },
    {
        "line_height": 0,
        "font_family": "ff2",
        "bottom": 717.94,
        "text": "",
        "font_size": 48.0,
        "text_shadow": "-0.015em 0 transparent,0 0.015em transparent,0.015em 0 transparent,0 -0.015em transparent",
        "left": 86.424,
        "data_offset_end": 61,
        "data_offset_start": 61,
        "level": "ATitle_9999",
        "height": 46.176
    },
    {
        "line_height": 0,
        "font_family": "ff1",
        "bottom": 703.18,
        "text": "十五  金融风险 (续 )",
        "font_size": 48.0,
        "text_shadow": "-0.015em 0 transparent,0 0.015em transparent,0.015em 0 transparent,0 -0.015em transparent",
        "left": 86.424,
        "data_offset_end": 73,
        "data_offset_start": 62,
        "level": "ATitle_9999",
        "height": 46.176
    },
    {
        "line_height": 0,
        "font_family": "ff2",
        "bottom": 688.54,
        "text": "",
        "font_size": 48.0,
        "text_shadow": "-0.015em 0 transparent,0 0.015em transparent,0.015em 0 transparent,0 -0.015em transparent",
        "left": 86.424,
        "data_offset_end": 74,
        "data_offset_start": 74,
        "level": "ATitle_9999",
        "height": 46.176
    },
    {
        "line_height": 0,
        "font_family": "ff2",
        "bottom": 673.78,
        "text": "(1)    市场风险 (续)",
        "font_size": 48.0,
        "text_shadow": "-0.015em 0 transparent,0 0.015em transparent,0.015em 0 transparent,0 -0.015em transparent",
        "left": 86.424,
        "data_offset_end": 88,
        "data_offset_start": 75,
        "level": "ATitle_9999",
        "height": 46.176
    },
    {
        "line_height": 0,
        "font_family": "ff2",
        "bottom": 659.26,
        "text": "",
        "font_size": 48.0,
        "text_shadow": "-0.015em 0 transparent,0 0.015em transparent,0.015em 0 transparent,0 -0.015em transparent",
        "left": 86.424,
        "data_offset_end": 89,
        "data_offset_start": 89,
        "level": "ATitle_9999",
        "height": 46.176
    },
    {
        "line_height": 0,
        "font_family": "ff2",
        "bottom": 644.5,
        "text": "(b)    利率风险",
        "font_size": 48.0,
        "text_shadow": "-0.015em 0 transparent,0 0.015em transparent,0.015em 0 transparent,0 -0.015em transparent",
        "left": 86.424,
        "data_offset_end": 100,
        "data_offset_start": 90,
        "level": "ATitle_9999",
        "height": 46.176
    },
    {
        "line_height": 0,
        "font_family": "ff2",
        "bottom": 629.86,
        "text": "",
        "font_size": 48.0,
        "text_shadow": "-0.015em 0 transparent,0 0.015em transparent,0.015em 0 transparent,0 -0.015em transparent",
        "left": 121.82,
        "data_offset_end": 101,
        "data_offset_start": 101,
        "level": "ATitle_9999",
        "height": 46.176
    },
    {
        "line_height": 0,
        "font_family": "ff4",
        "bottom": 615.1,
        "text": "本集团的利率风险主要产生于长期银行借款及应付债券等带息债务。 浮动利",
        "font_size": 48.0,
        "text_shadow": "-0.015em 0 transparent,0 0.015em transparent,0.015em 0 transparent,0 -0.015em transparent",
        "left": 121.82,
        "data_offset_end": 135,
        "data_offset_start": 102,
        "level": "ATitle_9999",
        "height": 39.9375
    },
    {
        "line_height": 0,
        "font_family": "ff4",
        "bottom": 599.5,
        "text": "率的金融负债使本集团面临现金流量利率风险，固定利率的金融负债 使本集",
        "font_size": 48.0,
        "text_shadow": "-0.015em 0 transparent,0 0.015em transparent,0.015em 0 transparent,0 -0.015em transparent",
        "left": 121.82,
        "data_offset_end": 169,
        "data_offset_start": 136,
        "level": "ATitle_9999",
        "height": 39.9375
    },
    {
        "line_height": 0,
        "font_family": "ff4",
        "bottom": 583.99,
        "text": "团面临公允价值利率风险。本集团根据当时的市场环境来决定固定利 率及浮",
        "font_size": 48.0,
        "text_shadow": "-0.015em 0 transparent,0 0.015em transparent,0.015em 0 transparent,0 -0.015em transparent",
        "left": 121.82,
        "data_offset_end": 203,
        "data_offset_start": 170,
        "level": "ATitle_9999",
        "height": 39.9375
    },
    {
        "line_height": 0,
        "font_family": "ff4",
        "bottom": 568.39,
        "text": "动利率合同的相对比例。于  2017  年12 月31  日，本集团无浮动利率带息长",
        "font_size": 48.0,
        "text_shadow": "-0.015em 0 transparent,0 0.015em transparent,0.015em 0 transparent,0 -0.015em transparent",
        "left": 121.82,
        "data_offset_end": 243,
        "data_offset_start": 204,
        "level": "ATitle_9999",
        "height": 46.176
    },
    {
        "line_height": 0,
        "font_family": "ff4",
        "bottom": 552.79,
        "text": "期债务金额 (2016  年12 月31 日： 71,560,000 元 )(附注四 (25))。",
        "font_size": 48.0,
        "text_shadow": "-0.015em 0 transparent,0 0.015em transparent,0.015em 0 transparent,0 -0.015em transparent",
        "left": 121.82,
        "data_offset_end": 289,
        "data_offset_start": 244,
        "level": "ATitle_9999",
        "height": 46.176
    },
    {
        "line_height": 0,
        "font_family": "ff2",
        "bottom": 538.27,
        "text": "",
        "font_size": 48.0,
        "text_shadow": "-0.015em 0 transparent,0 0.015em transparent,0.015em 0 transparent,0 -0.015em transparent",
        "left": 121.82,
        "data_offset_end": 290,
        "data_offset_start": 290,
        "level": "ATitle_9999",
        "height": 46.176
    },
    {
        "line_height": 0,
        "font_family": "ff4",
        "bottom": 523.51,
        "text": "本集团总部财务部门持续监控集团利率水平。利率上升会增加新增带 息债务",
        "font_size": 48.0,
        "text_shadow": "-0.015em 0 transparent,0 0.015em transparent,0.015em 0 transparent,0 -0.015em transparent",
        "left": 121.82,
        "data_offset_end": 324,
        "data_offset_start": 291,
        "level": "ATitle_9999",
        "height": 39.9375
    },
    {
        "line_height": 0,
        "font_family": "ff4",
        "bottom": 507.91,
        "text": "的成本以及本集团尚未付清的以浮动利率计息的带息债务的利息支出 ，并对",
        "font_size": 48.0,
        "text_shadow": "-0.015em 0 transparent,0 0.015em transparent,0.015em 0 transparent,0 -0.015em transparent",
        "left": 121.82,
        "data_offset_end": 358,
        "data_offset_start": 325,
        "level": "ATitle_9999",
        "height": 39.9375
    },
    {
        "line_height": 0,
        "font_family": "ff4",
        "bottom": 492.31,
        "text": "本集团的财务业绩产生重大的不利影响，管理层会依据最新的市场状 况及时",
        "font_size": 48.0,
        "text_shadow": "-0.015em 0 transparent,0 0.015em transparent,0.015em 0 transparent,0 -0.015em transparent",
        "left": 121.82,
        "data_offset_end": 392,
        "data_offset_start": 359,
        "level": "ATitle_9999",
        "height": 39.9375
    },
    {
        "line_height": 0,
        "font_family": "ff4",
        "bottom": 476.83,
        "text": "做出调整，这些调整可能是进行利率互换的安排来降低利率风险。",
        "font_size": 48.0,
        "text_shadow": "-0.015em 0 transparent,0 0.015em transparent,0.015em 0 transparent,0 -0.015em transparent",
        "left": 121.82,
        "data_offset_end": 423,
        "data_offset_start": 393,
        "level": "ATitle_9999",
        "height": 46.176
    },
    {
        "line_height": 0,
        "font_family": "ff2",
        "bottom": 462.19,
        "text": "(2)    信用风险",
        "font_size": 48.0,
        "text_shadow": "-0.015em 0 transparent,0 0.015em transparent,0.015em 0 transparent,0 -0.015em transparent",
        "left": 121.82,
        "data_offset_end": 435,
        "data_offset_start": 424,
        "level": "ATitle_9999",
        "height": 46.176
    },
    {
        "line_height": 0,
        "font_family": "ff2",
        "bottom": 432.79,
        "text": "",
        "font_size": 48.0,
        "text_shadow": "-0.015em 0 transparent,0 0.015em transparent,0.015em 0 transparent,0 -0.015em transparent",
        "left": 121.82,
        "data_offset_end": 436,
        "data_offset_start": 436,
        "level": "ATitle_9999",
        "height": 46.176
    },
    {
        "line_height": 0,
        "font_family": "ff4",
        "bottom": 418.01,
        "text": "本集团对信用风险按组合分类进行管理。信用风险主要产生于银行存款、存",
        "font_size": 48.0,
        "text_shadow": "-0.015em 0 transparent,0 0.015em transparent,0.015em 0 transparent,0 -0.015em transparent",
        "left": 121.82,
        "data_offset_end": 470,
        "data_offset_start": 437,
        "level": "ATitle_9999",
        "height": 39.9375
    },
    {
        "line_height": 0,
        "font_family": "ff4",
        "bottom": 402.41,
        "text": "放中央银行款项、存放同业款项、应收票据、应收账款、应收利息、发放贷",
        "font_size": 48.0,
        "text_shadow": "-0.015em 0 transparent,0 0.015em transparent,0.015em 0 transparent,0 -0.015em transparent",
        "left": 121.82,
        "data_offset_end": 504,
        "data_offset_start": 471,
        "level": "ATitle_9999",
        "height": 39.9375
    },
    {
        "line_height": 0,
        "font_family": "ff4",
        "bottom": 386.93,
        "text": "款和垫款、其他应收款及其他流动资产中的结构性存款等。",
        "font_size": 48.0,
        "text_shadow": "-0.015em 0 transparent,0 0.015em transparent,0.015em 0 transparent,0 -0.015em transparent",
        "left": 121.82,
        "data_offset_end": 532,
        "data_offset_start": 505,
        "level": "ATitle_9999",
        "height": 46.176
    },
    {
        "line_height": 0,
        "font_family": "ff2",
        "bottom": 372.29,
        "text": "",
        "font_size": 48.0,
        "text_shadow": "-0.015em 0 transparent,0 0.015em transparent,0.015em 0 transparent,0 -0.015em transparent",
        "left": 121.82,
        "data_offset_end": 533,
        "data_offset_start": 533,
        "level": "ATitle_9999",
        "height": 46.176
    },
    {
        "line_height": 0,
        "font_family": "ff4",
        "bottom": 357.53,
        "text": "本集团银行存款、存放中央银行款项及存放同业款项主要存放于国有银行和",
        "font_size": 48.0,
        "text_shadow": "-0.015em 0 transparent,0 0.015em transparent,0.015em 0 transparent,0 -0.015em transparent",
        "left": 121.82,
        "data_offset_end": 567,
        "data_offset_start": 534,
        "level": "ATitle_9999",
        "height": 39.9375
    },
    {
        "line_height": 0,
        "font_family": "ff4",
        "bottom": 341.93,
        "text": "其它大中型上市银行，本集团认为其不存在重大的信用风险，不会产生因对",
        "font_size": 48.0,
        "text_shadow": "-0.015em 0 transparent,0 0.015em transparent,0.015em 0 transparent,0 -0.015em transparent",
        "left": 121.82,
        "data_offset_end": 601,
        "data_offset_start": 568,
        "level": "ATitle_9999",
        "height": 39.9375
    },
    {
        "line_height": 0,
        "font_family": "ff4",
        "bottom": 326.45,
        "text": "方单位违约而导致的任何重大损失。",
        "font_size": 48.0,
        "text_shadow": "-0.015em 0 transparent,0 0.015em transparent,0.015em 0 transparent,0 -0.015em transparent",
        "left": 121.82,
        "data_offset_end": 619,
        "data_offset_start": 602,
        "level": "ATitle_9999",
        "height": 46.176
    },
    {
        "line_height": 0,
        "font_family": "ff2",
        "bottom": 311.81,
        "text": "",
        "font_size": 48.0,
        "text_shadow": "-0.015em 0 transparent,0 0.015em transparent,0.015em 0 transparent,0 -0.015em transparent",
        "left": 121.82,
        "data_offset_end": 620,
        "data_offset_start": 620,
        "level": "ATitle_9999",
        "height": 46.176
    },
    {
        "line_height": 0,
        "font_family": "ff4",
        "bottom": 297.05,
        "text": "此外，对于应收票据 、应收账款、应收利息 、发放贷款和垫款 、其他应收款",
        "font_size": 48.0,
        "text_shadow": "-0.015em 0 transparent,0 0.015em transparent,0.015em 0 transparent,0 -0.015em transparent",
        "left": 121.82,
        "data_offset_end": 654,
        "data_offset_start": 621,
        "level": "ATitle_9999",
        "height": 39.9375
    },
    {
        "line_height": 0,
        "font_family": "ff4",
        "bottom": 281.45,
        "text": "及其他流动资产中的结构性存款， 本集团设定相关政策以控制信用风险敞口。",
        "font_size": 48.0,
        "text_shadow": "-0.015em 0 transparent,0 0.015em transparent,0.015em 0 transparent,0 -0.015em transparent",
        "left": 121.82,
        "data_offset_end": 689,
        "data_offset_start": 655,
        "level": "ATitle_9999",
        "height": 39.9375
    },
    {
        "line_height": 0,
        "font_family": "ff4",
        "bottom": 265.97,
        "text": "本集团基于对客户的财务状况、从第三方获取担保的可能性、信用记 录及其",
        "font_size": 48.0,
        "text_shadow": "-0.015em 0 transparent,0 0.015em transparent,0.015em 0 transparent,0 -0.015em transparent",
        "left": 121.82,
        "data_offset_end": 723,
        "data_offset_start": 690,
        "level": "ATitle_9999",
        "height": 39.9375
    },
    {
        "line_height": 0,
        "font_family": "ff4",
        "bottom": 250.34,
        "text": "它因素诸如目前市场状况等评估客户的信用资质并设置相应信用期。 本集团",
        "font_size": 48.0,
        "text_shadow": "-0.015em 0 transparent,0 0.015em transparent,0.015em 0 transparent,0 -0.015em transparent",
        "left": 121.82,
        "data_offset_end": 757,
        "data_offset_start": 724,
        "level": "ATitle_9999",
        "height": 39.9375
    },
    {
        "line_height": 0,
        "font_family": "ff4",
        "bottom": 234.74,
        "text": "会定期对客户信用记录进行监控，对于信用记录不良的客户，本集团 会采用",
        "font_size": 48.0,
        "text_shadow": "-0.015em 0 transparent,0 0.015em transparent,0.015em 0 transparent,0 -0.015em transparent",
        "left": 121.82,
        "data_offset_end": 791,
        "data_offset_start": 758,
        "level": "ATitle_9999",
        "height": 39.9375
    },
    {
        "line_height": 0,
        "font_family": "ff4",
        "bottom": 219.26,
        "text": "书面催款、缩短信用期或取消信用期等方式，以确保本集团的整体信 用风险",
        "font_size": 48.0,
        "text_shadow": "-0.015em 0 transparent,0 0.015em transparent,0.015em 0 transparent,0 -0.015em transparent",
        "left": 121.82,
        "data_offset_end": 825,
        "data_offset_start": 792,
        "level": "ATitle_9999",
        "height": 39.9375
    },
    {
        "line_height": 0,
        "font_family": "ff4",
        "bottom": 203.66,
        "text": "在可控的范围内。",
        "font_size": 48.0,
        "text_shadow": "-0.015em 0 transparent,0 0.015em transparent,0.015em 0 transparent,0 -0.015em transparent",
        "left": 121.82,
        "data_offset_end": 838,
        "data_offset_start": 826,
        "level": "ATitle_9999",
        "height": 46.176
    }
]