[
    {
        "line_height": 0,
        "font_family": "ff1",
        "bottom": 790.32,
        "text": "美的集团股份有限公司  2017  年年度报告71",
        "font_size": 36.0,
        "text_shadow": "-0.015em 0 transparent,0 0.015em transparent,0.015em 0 transparent,0 -0.015em transparent",
        "left": 381.07,
        "data_offset_end": 32,
        "data_offset_start": 6,
        "level": "BTitle_9999",
        "height": 33.66
    },
    {
        "line_height": 0,
        "font_family": "ff1",
        "bottom": 754.44,
        "text": "员的薪酬由基本 年薪和绩效年薪 构成。 基本薪酬 根据董事、 监事与高级管 理人员所承担 的责任、 风险、 压",
        "font_size": 42.24,
        "text_shadow": "-0.015em 0 transparent,0 0.015em transparent,0.015em 0 transparent,0 -0.015em transparent",
        "left": 56.664,
        "data_offset_end": 79,
        "data_offset_start": 33,
        "level": "Text_9999",
        "height": 35.145
    },
    {
        "line_height": 0,
        "font_family": "ff1",
        "bottom": 731.02,
        "text": "力等确定， 基本年薪保持 稳定， 绩效年薪与公司利 润完成率、 目标责任制考 核结果及所在部 门的绩效考 评",
        "font_size": 42.24,
        "text_shadow": "-0.015em 0 transparent,0 0.015em transparent,0.015em 0 transparent,0 -0.015em transparent",
        "left": 56.664,
        "data_offset_end": 126,
        "data_offset_start": 80,
        "level": "Text_9999",
        "height": 35.145
    },
    {
        "line_height": 0,
        "font_family": "ff1",
        "bottom": 707.62,
        "text": "结构挂钩。 公司董事、 监事和高 级管理人员的 薪酬体系为公司 的经营战略服 务， 并随着公司经营状况 的不",
        "font_size": 42.24,
        "text_shadow": "-0.015em 0 transparent,0 0.015em transparent,0.015em 0 transparent,0 -0.015em transparent",
        "left": 56.664,
        "data_offset_end": 173,
        "data_offset_start": 127,
        "level": "Text_9999",
        "height": 35.145
    },
    {
        "line_height": 0,
        "font_family": "ff1",
        "bottom": 684.22,
        "text": "断变化而作相应 的调整以适应公 司的进一步发 展需要。 公司董事、 监事及高 级管理人员的 薪酬调整依据 为：",
        "font_size": 42.24,
        "text_shadow": "-0.015em 0 transparent,0 0.015em transparent,0.015em 0 transparent,0 -0.015em transparent",
        "left": 56.664,
        "data_offset_end": 221,
        "data_offset_start": 174,
        "level": "Text_9999",
        "height": 35.145
    },
    {
        "line_height": 0,
        "font_family": "ff1",
        "bottom": 660.82,
        "text": "（ 1）同行业薪 资增幅水平 ； （ 2）通胀水平 ； （ 3）公司盈利 状况； （ 4）组 织结构调整情况； （ 5）岗 位发生",
        "font_size": 42.24,
        "text_shadow": "-0.015em 0 transparent,0 0.015em transparent,0.015em 0 transparent,0 -0.015em transparent",
        "left": 56.664,
        "data_offset_end": 272,
        "data_offset_start": 222,
        "level": "Text_9999",
        "height": 35.145
    },
    {
        "line_height": 0,
        "font_family": "ff1",
        "bottom": 637.42,
        "text": "变动的个别调整 等。",
        "font_size": 42.24,
        "text_shadow": "-0.015em 0 transparent,0 0.015em transparent,0.015em 0 transparent,0 -0.015em transparent",
        "left": 56.664,
        "data_offset_end": 283,
        "data_offset_start": 273,
        "level": "Text_9999",
        "height": 35.145
    },
    {
        "line_height": 0,
        "font_family": "ff1",
        "bottom": 611.74,
        "text": "公司报告期内董 事、监事和高级 管理人员报酬 情况",
        "font_size": 42.24,
        "text_shadow": "-0.015em 0 transparent,0 0.015em transparent,0.015em 0 transparent,0 -0.015em transparent",
        "left": 56.664,
        "data_offset_end": 307,
        "data_offset_start": 284,
        "level": "Text_9999",
        "height": 35.145
    },
    {
        "line_height": 0,
        "font_family": "ff1",
        "bottom": 590.98,
        "text": "单位：万元姓名职务性别年龄任职状态从公司获得的税前报酬总额是否在公司关联方获取报酬方洪波董事长、总裁男51现任719何剑锋董事男51现任是殷必彤董事、副总裁男50现任420朱凤涛董事、副总裁男50现任382顾炎民董事、副总裁男55现任291李飞德董事、副总裁男41现任196吴世农独立董事男62现任15芮萌独立董事男51现任15郭学进独立董事男59现任15黎文靖独立董事男39现任15刘敏监事会主席女41现任154赵军监事男43现任是梁惠铭职工代表监事女35现任17王金亮副总裁男51现任175王建国副总裁男42现任317胡自强副总裁男61现任429向卫民副总裁男52现任324肖明光财务总监男48现任196江鹏董事会秘书男45现任179吴文新董事、副总裁男54离任249麦钰芬职工代表监事女34离任25胡晓玲董事女48离任否合计--------4,133--",
        "font_size": 36.0,
        "text_shadow": "-0.015em 0 transparent,0 0.015em transparent,0.015em 0 transparent,0 -0.015em transparent",
        "left": 493.66,
        "data_offset_end": 1005,
        "data_offset_start": 308,
        "level": "BTitle_9999",
        "height": 33.66
    }
]