[
    {
        "line_height": 0,
        "font_family": "ff1",
        "bottom": 785.4,
        "text": "美的集团股份有限公司",
        "font_size": 48.0,
        "text_shadow": "-0.015em 0 transparent,0 0.015em transparent,0.015em 0 transparent,0 -0.015em transparent",
        "left": 121.82,
        "data_offset_end": 17,
        "data_offset_start": 6,
        "level": "ATitle_9999",
        "height": 46.176
    },
    {
        "line_height": 0,
        "font_family": "ff2",
        "bottom": 768.84,
        "text": "",
        "font_size": 48.0,
        "text_shadow": "-0.015em 0 transparent,0 0.015em transparent,0.015em 0 transparent,0 -0.015em transparent",
        "left": 121.82,
        "data_offset_end": 18,
        "data_offset_start": 18,
        "level": "ATitle_9999",
        "height": 46.176
    },
    {
        "line_height": 0,
        "font_family": "ff2",
        "bottom": 752.14,
        "text": "2017  年度财务报表附注",
        "font_size": 48.0,
        "text_shadow": "-0.015em 0 transparent,0 0.015em transparent,0.015em 0 transparent,0 -0.015em transparent",
        "left": 121.82,
        "data_offset_end": 33,
        "data_offset_start": 19,
        "level": "ATitle_9999",
        "height": 46.176
    },
    {
        "line_height": 0,
        "font_family": "ff3",
        "bottom": 734.5,
        "text": "( 除特别注明外，金额单位为人民币千元 )",
        "font_size": 48.0,
        "text_shadow": "-0.015em 0 transparent,0 0.015em transparent,0.015em 0 transparent,0 -0.015em transparent",
        "left": 121.82,
        "data_offset_end": 55,
        "data_offset_start": 34,
        "level": "ATitle_9999",
        "height": 44.88
    },
    {
        "line_height": 0,
        "font_family": "ff2",
        "bottom": 38.4,
        "text": "184",
        "font_size": 36.0,
        "text_shadow": "-0.015em 0 transparent,0 0.015em transparent,0.015em 0 transparent,0 -0.015em transparent",
        "left": 297.43,
        "data_offset_end": 60,
        "data_offset_start": 56,
        "level": "BTitle_9999",
        "height": 34.632
    },
    {
        "line_height": 0,
        "font_family": "ff2",
        "bottom": 717.94,
        "text": "",
        "font_size": 48.0,
        "text_shadow": "-0.015em 0 transparent,0 0.015em transparent,0.015em 0 transparent,0 -0.015em transparent",
        "left": 86.424,
        "data_offset_end": 61,
        "data_offset_start": 61,
        "level": "ATitle_9999",
        "height": 46.176
    },
    {
        "line_height": 0,
        "font_family": "ff1",
        "bottom": 703.18,
        "text": "十五  金融风险 (续 )",
        "font_size": 48.0,
        "text_shadow": "-0.015em 0 transparent,0 0.015em transparent,0.015em 0 transparent,0 -0.015em transparent",
        "left": 86.424,
        "data_offset_end": 73,
        "data_offset_start": 62,
        "level": "ATitle_9999",
        "height": 46.176
    },
    {
        "line_height": 0,
        "font_family": "ff2",
        "bottom": 688.54,
        "text": "",
        "font_size": 48.0,
        "text_shadow": "-0.015em 0 transparent,0 0.015em transparent,0.015em 0 transparent,0 -0.015em transparent",
        "left": 86.424,
        "data_offset_end": 74,
        "data_offset_start": 74,
        "level": "ATitle_9999",
        "height": 46.176
    },
    {
        "line_height": 0,
        "font_family": "ff2",
        "bottom": 673.78,
        "text": "(3)    流动性风险",
        "font_size": 48.0,
        "text_shadow": "-0.015em 0 transparent,0 0.015em transparent,0.015em 0 transparent,0 -0.015em transparent",
        "left": 86.424,
        "data_offset_end": 86,
        "data_offset_start": 75,
        "level": "ATitle_9999",
        "height": 46.176
    },
    {
        "line_height": 0,
        "font_family": "ff2",
        "bottom": 659.26,
        "text": "",
        "font_size": 48.0,
        "text_shadow": "-0.015em 0 transparent,0 0.015em transparent,0.015em 0 transparent,0 -0.015em transparent",
        "left": 86.424,
        "data_offset_end": 87,
        "data_offset_start": 87,
        "level": "ATitle_9999",
        "height": 46.176
    },
    {
        "line_height": 0,
        "font_family": "ff4",
        "bottom": 644.5,
        "text": "本集团内各子公司负责其自身的现金流量预测。总部财务部门在汇总 各子公",
        "font_size": 48.0,
        "text_shadow": "-0.015em 0 transparent,0 0.015em transparent,0.015em 0 transparent,0 -0.015em transparent",
        "left": 121.82,
        "data_offset_end": 121,
        "data_offset_start": 88,
        "level": "Text_9999",
        "height": 39.9375
    },
    {
        "line_height": 0,
        "font_family": "ff4",
        "bottom": 628.9,
        "text": "司现金流量预测的基础上，在集团层面持续监控短期和长期的资金需 求，以",
        "font_size": 48.0,
        "text_shadow": "-0.015em 0 transparent,0 0.015em transparent,0.015em 0 transparent,0 -0.015em transparent",
        "left": 121.82,
        "data_offset_end": 155,
        "data_offset_start": 122,
        "level": "Text_9999",
        "height": 39.9375
    },
    {
        "line_height": 0,
        "font_family": "ff4",
        "bottom": 613.3,
        "text": "确保维持充裕的现金储备和可供随时变现的有价证券；同时持续监控 是否符",
        "font_size": 48.0,
        "text_shadow": "-0.015em 0 transparent,0 0.015em transparent,0.015em 0 transparent,0 -0.015em transparent",
        "left": 121.82,
        "data_offset_end": 189,
        "data_offset_start": 156,
        "level": "Text_9999",
        "height": 39.9375
    },
    {
        "line_height": 0,
        "font_family": "ff4",
        "bottom": 597.82,
        "text": "合借款协议的规定，从主要金融机构获得提供足够备用资金的承诺， 以满足",
        "font_size": 48.0,
        "text_shadow": "-0.015em 0 transparent,0 0.015em transparent,0.015em 0 transparent,0 -0.015em transparent",
        "left": 121.82,
        "data_offset_end": 223,
        "data_offset_start": 190,
        "level": "Text_9999",
        "height": 39.9375
    },
    {
        "line_height": 0,
        "font_family": "ff4",
        "bottom": 582.19,
        "text": "短期和长期的资金需求。 于资产负债表日 ,本集团持有的货币资金、 票据资产、",
        "font_size": 48.0,
        "text_shadow": "-0.015em 0 transparent,0 0.015em transparent,0.015em 0 transparent,0 -0.015em transparent",
        "left": 121.82,
        "data_offset_end": 259,
        "data_offset_start": 224,
        "level": "Text_9999",
        "height": 46.176
    },
    {
        "line_height": 0,
        "font_family": "ff4",
        "bottom": 566.59,
        "text": "贴现资产、包括在其他流动资产及可供出售 金融资产中的理财资金 等货币性",
        "font_size": 48.0,
        "text_shadow": "-0.015em 0 transparent,0 0.015em transparent,0.015em 0 transparent,0 -0.015em transparent",
        "left": 121.82,
        "data_offset_end": 293,
        "data_offset_start": 260,
        "level": "Text_9999",
        "height": 39.9375
    },
    {
        "line_height": 0,
        "font_family": "ff4",
        "bottom": 551.11,
        "text": "资产合计为人民币  109,654,798,000 元。",
        "font_size": 48.0,
        "text_shadow": "-0.015em 0 transparent,0 0.015em transparent,0.015em 0 transparent,0 -0.015em transparent",
        "left": 121.82,
        "data_offset_end": 322,
        "data_offset_start": 294,
        "level": "Text_9999",
        "height": 46.176
    },
    {
        "line_height": 0,
        "font_family": "ff2",
        "bottom": 536.47,
        "text": "",
        "font_size": 48.0,
        "text_shadow": "-0.015em 0 transparent,0 0.015em transparent,0.015em 0 transparent,0 -0.015em transparent",
        "left": 121.82,
        "data_offset_end": 323,
        "data_offset_start": 323,
        "level": "Text_9999",
        "height": 46.176
    },
    {
        "line_height": 0,
        "font_family": "ff4",
        "bottom": 521.71,
        "text": "于资产负债表日，本集团各项金融负债以未折现的合同现金流量按到期日列",
        "font_size": 48.0,
        "text_shadow": "-0.015em 0 transparent,0 0.015em transparent,0.015em 0 transparent,0 -0.015em transparent",
        "left": 121.82,
        "data_offset_end": 357,
        "data_offset_start": 324,
        "level": "Text_9999",
        "height": 39.9375
    },
    {
        "line_height": 0,
        "font_family": "ff4",
        "bottom": 506.11,
        "text": "示如下：",
        "font_size": 48.0,
        "text_shadow": "-0.015em 0 transparent,0 0.015em transparent,0.015em 0 transparent,0 -0.015em transparent",
        "left": 121.82,
        "data_offset_end": 363,
        "data_offset_start": 358,
        "level": "Text_9999",
        "height": 46.176
    },
    {
        "line_height": 0,
        "font_family": "ff5",
        "bottom": 492.31,
        "text": "",
        "font_size": 44.16,
        "text_shadow": "-0.015em 0 transparent,0 0.015em transparent,0.015em 0 transparent,0 -0.015em transparent",
        "left": 121.82,
        "data_offset_end": 364,
        "data_offset_start": 364,
        "level": "BTitle_9999",
        "height": 30.122812
    },
    {
        "line_height": 0,
        "font_family": "ff2",
        "bottom": 0,
        "text": "2017  年 12 月31 日一年以内一到二年二到五年五年以上合计短期借款 (包括利息 )2,602,067---2,602,067应付票据25,207,785---25,207,785应付账款35,144,777---35,144,777应付利息94,801---94,801应付股利95,317---95,317其他应付款3,170,405---3,170,405吸收存款及同业存放108,926---108,926衍生金融负债90,432---90,432其他流动负债9,017,975---9,017,975应付债券（包括利息）108,6314,682,571--4,791,202长期借款 (包括利息 )306,7232,415,50831,643,9352,08734,368,253其他非流动负债-189,404138,643666,012994,05975,947,8397,287,48331,782,578668,099115,685,999",
        "font_size": 32.16,
        "text_shadow": "-0.015em 0 transparent,0 0.015em transparent,0.015em 0 transparent,0 -0.015em transparent",
        "left": 5.393,
        "data_offset_end": 1041,
        "data_offset_start": 365,
        "level": "BTitle_9999",
        "height": 30.93792
    },
    {
        "line_height": 0,
        "font_family": "ff3",
        "bottom": 288.41,
        "text": "",
        "font_size": 32.16,
        "text_shadow": "-0.015em 0 transparent,0 0.015em transparent,0.015em 0 transparent,0 -0.015em transparent",
        "left": 121.82,
        "data_offset_end": 1043,
        "data_offset_start": 1042,
        "level": "BTitle_9999",
        "height": 30.0696
    },
    {
        "line_height": 0,
        "font_family": "ff2",
        "bottom": 2.4,
        "text": "2016  年 12 月31 日一年以内一到二年二到五年五年以上合计短期借款 (包括利息 )3,104,224---3,104,224应付票据18,484,939---18,484,939应付账款25,356,960---25,356,960应付利息21,343---21,343应付股利105,641---105,641其他应付款1,571,422---1,571,422吸收存款及同业存放36,708---36,708衍生金融负债89,838---89,838其他流动负债8,342,926---8,342,926应付债券（包括利息）115,328115,3284,913,564-5,144,220长期借款 (包括利息 )60,64855,6132,187,3895842,304,234其他非流动负债--222,140666,012888,15257,289,977170,9417,323,093666,59665,450,607",
        "font_size": 32.16,
        "text_shadow": "-0.015em 0 transparent,0 0.015em transparent,0.015em 0 transparent,0 -0.015em transparent",
        "left": 124.22,
        "data_offset_end": 1691,
        "data_offset_start": 1044,
        "level": "BTitle_9999",
        "height": 30.93792
    },
    {
        "line_height": 0,
        "font_family": "ff2",
        "bottom": 81.72,
        "text": "",
        "font_size": 48.0,
        "text_shadow": "-0.015em 0 transparent,0 0.015em transparent,0.015em 0 transparent,0 -0.015em transparent",
        "left": 86.424,
        "data_offset_end": 1692,
        "data_offset_start": 1692,
        "level": "ATitle_9999",
        "height": 46.176
    },
    {
        "line_height": 0,
        "font_family": "ff2",
        "bottom": 67.92,
        "text": "",
        "font_size": 48.0,
        "text_shadow": "-0.015em 0 transparent,0 0.015em transparent,0.015em 0 transparent,0 -0.015em transparent",
        "left": 86.424,
        "data_offset_end": 1695,
        "data_offset_start": 1693,
        "level": "ATitle_9999",
        "height": 46.176
    }
]